<?xml version="1.0" encoding="UTF-8"?>
<!DOCTYPE mapper PUBLIC "-//mybatis.org//DTD Mapper 3.0//EN" "http://mybatis.org/dtd/mybatis-3-mapper.dtd">
<mapper namespace="com.mengka.springboot.dao.persistence.RepositoryDOMapper">
  <resultMap id="BaseResultMap" type="com.mengka.springboot.dao.domain.RepositoryDO">
    <!--
      WARNING - @mbg.generated
      This element is automatically generated by MyBatis Generator, do not modify.
    -->
    <id column="id" jdbcType="BIGINT" property="id" />
    <result column="owner_id" jdbcType="BIGINT" property="ownerId" />
    <result column="lower_name" jdbcType="VARCHAR" property="lowerName" />
    <result column="name" jdbcType="VARCHAR" property="name" />
    <result column="description" jdbcType="VARCHAR" property="description" />
    <result column="default_branch" jdbcType="VARCHAR" property="defaultBranch" />
    <result column="create_time" jdbcType="TIMESTAMP" property="createTime" />
    <result column="update_time" jdbcType="TIMESTAMP" property="updateTime" />
    <result column="parent_id" jdbcType="BIGINT" property="parentId" />
  </resultMap>
  <sql id="Base_Column_List">
    <!--
      WARNING - @mbg.generated
      This element is automatically generated by MyBatis Generator, do not modify.
    -->
    id, owner_id, lower_name, name, description, default_branch, create_time, update_time, 
    parent_id
  </sql>
  <select id="selectByPrimaryKey" parameterType="java.lang.Long" resultMap="BaseResultMap">
    <!--
      WARNING - @mbg.generated
      This element is automatically generated by MyBatis Generator, do not modify.
    -->
    select 
    <include refid="Base_Column_List" />
    from g_repository
    where id = #{id,jdbcType=BIGINT}
  </select>
  <select id="selectByParentId" parameterType="java.lang.Long" resultMap="BaseResultMap">
    select
    <include refid="Base_Column_List" />
    from g_repository
    where parent_id = #{parentId}
  </select>
  <delete id="deleteByPrimaryKey" parameterType="java.lang.Long">
    <!--
      WARNING - @mbg.generated
      This element is automatically generated by MyBatis Generator, do not modify.
    -->
    delete from g_repository
    where id = #{id,jdbcType=BIGINT}
  </delete>
  <insert id="insert" parameterType="com.mengka.springboot.dao.domain.RepositoryDO">
    <!--
      WARNING - @mbg.generated
      This element is automatically generated by MyBatis Generator, do not modify.
    -->
    insert into g_repository (id, owner_id, lower_name, 
      name, description, default_branch, 
      create_time, update_time, parent_id
      )
    values (#{id,jdbcType=BIGINT}, #{ownerId,jdbcType=BIGINT}, #{lowerName,jdbcType=VARCHAR}, 
      #{name,jdbcType=VARCHAR}, #{description,jdbcType=VARCHAR}, #{defaultBranch,jdbcType=VARCHAR}, 
      #{createTime,jdbcType=TIMESTAMP}, #{updateTime,jdbcType=TIMESTAMP}, #{parentId,jdbcType=BIGINT}
      )
  </insert>

  <insert id="batchInsertAndUpdate" parameterType="java.util.List" useGeneratedKeys="true">
    INSERT INTO g_repository (id, owner_id, lower_name,
    name, description, default_branch,
    create_time, update_time, parent_id)
    VALUES
    <foreach collection="list"  separator="," item="item">
      (#{item.id,jdbcType=BIGINT}, #{item.ownerId,jdbcType=BIGINT}, #{item.lowerName,jdbcType=VARCHAR},
      #{item.name,jdbcType=VARCHAR}, #{item.description,jdbcType=VARCHAR}, #{item.defaultBranch,jdbcType=VARCHAR},
      #{item.createTime,jdbcType=TIMESTAMP}, #{item.updateTime,jdbcType=TIMESTAMP}, #{item.parentId,jdbcType=BIGINT}
      )
    </foreach>
    ON DUPLICATE KEY UPDATE update_time=#{updateTime,jdbcType=TIMESTAMP};
  </insert>

  <select id="selectByCode" resultMap="BaseResultMap">
    select
    <include refid="Base_Column_List" />
    from g_repository
    where parent_id = #{parentId} and lower_name = #{lowerName,jdbcType=VARCHAR}
  </select>

  <insert id="insertSelective" parameterType="com.mengka.springboot.dao.domain.RepositoryDO">
    <!--
      WARNING - @mbg.generated
      This element is automatically generated by MyBatis Generator, do not modify.
    -->
    insert into g_repository
    <trim prefix="(" suffix=")" suffixOverrides=",">
      <if test="id != null">
        id,
      </if>
      <if test="ownerId != null">
        owner_id,
      </if>
      <if test="lowerName != null">
        lower_name,
      </if>
      <if test="name != null">
        name,
      </if>
      <if test="description != null">
        description,
      </if>
      <if test="defaultBranch != null">
        default_branch,
      </if>
      <if test="createTime != null">
        create_time,
      </if>
      <if test="updateTime != null">
        update_time,
      </if>
      <if test="parentId != null">
        parent_id,
      </if>
    </trim>
    <trim prefix="values (" suffix=")" suffixOverrides=",">
      <if test="id != null">
        #{id,jdbcType=BIGINT},
      </if>
      <if test="ownerId != null">
        #{ownerId,jdbcType=BIGINT},
      </if>
      <if test="lowerName != null">
        #{lowerName,jdbcType=VARCHAR},
      </if>
      <if test="name != null">
        #{name,jdbcType=VARCHAR},
      </if>
      <if test="description != null">
        #{description,jdbcType=VARCHAR},
      </if>
      <if test="defaultBranch != null">
        #{defaultBranch,jdbcType=VARCHAR},
      </if>
      <if test="createTime != null">
        #{createTime,jdbcType=TIMESTAMP},
      </if>
      <if test="updateTime != null">
        #{updateTime,jdbcType=TIMESTAMP},
      </if>
      <if test="parentId != null">
        #{parentId,jdbcType=BIGINT},
      </if>
    </trim>
  </insert>
  <update id="updateByPrimaryKeySelective" parameterType="com.mengka.springboot.dao.domain.RepositoryDO">
    <!--
      WARNING - @mbg.generated
      This element is automatically generated by MyBatis Generator, do not modify.
    -->
    update g_repository
    <set>
      <if test="ownerId != null">
        owner_id = #{ownerId,jdbcType=BIGINT},
      </if>
      <if test="lowerName != null">
        lower_name = #{lowerName,jdbcType=VARCHAR},
      </if>
      <if test="name != null">
        name = #{name,jdbcType=VARCHAR},
      </if>
      <if test="description != null">
        description = #{description,jdbcType=VARCHAR},
      </if>
      <if test="defaultBranch != null">
        default_branch = #{defaultBranch,jdbcType=VARCHAR},
      </if>
      <if test="createTime != null">
        create_time = #{createTime,jdbcType=TIMESTAMP},
      </if>
      <if test="updateTime != null">
        update_time = #{updateTime,jdbcType=TIMESTAMP},
      </if>
      <if test="parentId != null">
        parent_id = #{parentId,jdbcType=BIGINT},
      </if>
    </set>
    where id = #{id,jdbcType=BIGINT}
  </update>
  <update id="updateByPrimaryKey" parameterType="com.mengka.springboot.dao.domain.RepositoryDO">
    <!--
      WARNING - @mbg.generated
      This element is automatically generated by MyBatis Generator, do not modify.
    -->
    update g_repository
    set owner_id = #{ownerId,jdbcType=BIGINT},
      lower_name = #{lowerName,jdbcType=VARCHAR},
      name = #{name,jdbcType=VARCHAR},
      description = #{description,jdbcType=VARCHAR},
      default_branch = #{defaultBranch,jdbcType=VARCHAR},
      create_time = #{createTime,jdbcType=TIMESTAMP},
      update_time = #{updateTime,jdbcType=TIMESTAMP},
      parent_id = #{parentId,jdbcType=BIGINT}
    where id = #{id,jdbcType=BIGINT}
  </update>
</mapper>